MANIFEST.in
README.md
setup.py
dash_progress_bar/LineProgressBarComponent.py
dash_progress_bar/__init__.py
dash_progress_bar/_imports_.py
dash_progress_bar/dash_progress_bar.dev.js
dash_progress_bar/dash_progress_bar.min.js
dash_progress_bar/metadata.json
dash_progress_bar/package.json
dash_progress_bar.egg-info/PKG-INFO
dash_progress_bar.egg-info/SOURCES.txt
dash_progress_bar.egg-info/dependency_links.txt
dash_progress_bar.egg-info/top_level.txt