Metadata-Version: 1.0
Name: dash-progress-bar
Version: 0.0.1
Summary: Project Description
Home-page: UNKNOWN
Author: byron byron@plot.ly
Author-email: UNKNOWN
License: MIT
Platform: UNKNOWN
